setup.py
emigrate/Frame.py
emigrate/Sequence.py
emigrate/Solver.py
emigrate/__init__.py
emigrate/__main__.py
emigrate/__version__.py
emigrate/deserialize.py
emigrate/preconditioner.py
emigrate/tests.py
emigrate.egg-info/PKG-INFO
emigrate.egg-info/SOURCES.txt
emigrate.egg-info/dependency_links.txt
emigrate.egg-info/entry_points.txt
emigrate.egg-info/pbr.json
emigrate.egg-info/top_level.txt
emigrate/equilibration_schemes/Equilibrator.py
emigrate/equilibration_schemes/Fixed.py
emigrate/equilibration_schemes/Multiroot.py
emigrate/equilibration_schemes/VariablepH.py
emigrate/equilibration_schemes/__init__.py
emigrate/equilibration_schemes/fixed.py
emigrate/equilibration_schemes/multiroot.py
emigrate/flux_schemes/Compact.py
emigrate/flux_schemes/Differentiate.py
emigrate/flux_schemes/Flux_Limiter.py
emigrate/flux_schemes/Fluxer.py
emigrate/flux_schemes/SLIP.py
emigrate/flux_schemes/__init__.py
emigrate/flux_schemes/boundary_characteristic.py
emigrate/flux_schemes/compact.py