Metadata-Version: 1.1
Name: emigrate
Version: 0.14.0
Summary: A package for simulating electrophoresis.
Home-page: https://github.com/lewisamarshall/emigrate
Author: Lewis A. Marshall
Author-email: lewis.a.marshall@gmail.com
License: UNKNOWN
Platform: UNKNOWN
Classifier: Programming Language :: Python
Classifier: Development Status :: 3 - Alpha
Classifier: Environment :: Console
Classifier: Intended Audience :: Science/Research
Classifier: Operating System :: OS Independent
Classifier: Topic :: Software Development :: Libraries :: Python Modules
Classifier: Topic :: Scientific/Engineering :: Chemistry
Requires: numpy
Requires: scipy
Requires: ionize
Requires: h5py
Requires: ionize
